LICENSE.txt
README.md
setup.cfg
setup.py
py_tweet_format/__init__.py
py_tweet_format/__main__.py
py_tweet_format.egg-info/PKG-INFO
py_tweet_format.egg-info/SOURCES.txt
py_tweet_format.egg-info/dependency_links.txt
py_tweet_format.egg-info/entry_points.txt
py_tweet_format.egg-info/top_level.txt